package com.jirbo.adcolony;

import java.io.File;
import java.util.List;
import java.util.Map;
import javax.net.ssl.SSLContext;

class ADCDownload
  extends j
  implements Runnable
{
  private static final String r = "okio error, disabling AdColony";
  d a;
  Listener b;
  String c = "";
  File d;
  Object e;
  String f;
  String g;
  boolean h;
  boolean i;
  int j;
  boolean k;
  long l = System.currentTimeMillis();
  Map<String, List<String>> m;
  SSLContext n;
  int o;
  String p;
  
  ADCDownload(d paramd, String paramString, Listener paramListener)
  {
    this(paramd, paramString, paramListener, null);
  }
  
  ADCDownload(d paramd, String paramString1, Listener paramListener, String paramString2)
  {
    super(paramd, false);
    this.c = paramString1;
    if (paramString1 == null) {
      this.c = "";
    }
    this.b = paramListener;
    if (paramString2 != null) {
      this.d = new File(paramString2);
    }
  }
  
  ADCDownload a(Object paramObject)
  {
    this.e = paramObject;
    return this;
  }
  
  ADCDownload a(String paramString1, String paramString2)
  {
    this.f = paramString1;
    this.g = paramString2;
    return this;
  }
  
  void a()
  {
    this.b.on_download_finished(this);
  }
  
  void a(Object paramObject, boolean paramBoolean)
  {
    if ((paramObject instanceof o.a))
    {
      if (paramBoolean) {
        ((o.a)paramObject).i = (System.currentTimeMillis() - this.l);
      }
    }
    else {
      return;
    }
    ((o.a)paramObject).j = (System.currentTimeMillis() - this.l);
  }
  
  public void b()
  {
    z.a(this);
  }
  
  void c()
  {
    if ((this.e instanceof o.a))
    {
      o.a locala = (o.a)this.e;
      ADCData.g localg = new ADCData.g();
      localg.b("url", locala.a);
      localg.b("success", this.i);
      localg.b("attempts", this.j);
      localg.b("connection", locala.l);
      localg.b("first_byte", (float)locala.i / 1000.0F);
      localg.b("last_byte", (float)locala.j / 1000.0F);
      localg.b("size", this.o);
      a.l.d.g.a(localg);
    }
  }
  
  /* Error */
  public void run()
  {
    // Byte code:
    //   0: iconst_1
    //   1: istore 4
    //   3: iload 4
    //   5: iconst_3
    //   6: if_icmpgt +386 -> 392
    //   9: aconst_null
    //   10: astore 8
    //   12: aconst_null
    //   13: astore 9
    //   15: new 169	java/net/URL
    //   18: dup
    //   19: aload_0
    //   20: getfield 52	com/jirbo/adcolony/ADCDownload:c	Ljava/lang/String;
    //   23: invokespecial 170	java/net/URL:<init>	(Ljava/lang/String;)V
    //   26: invokevirtual 174	java/net/URL:openConnection	()Ljava/net/URLConnection;
    //   29: checkcast 176	java/net/HttpURLConnection
    //   32: checkcast 176	java/net/HttpURLConnection
    //   35: astore 10
    //   37: aload_0
    //   38: getfield 75	com/jirbo/adcolony/ADCDownload:f	Ljava/lang/String;
    //   41: ifnull +570 -> 611
    //   44: getstatic 181	com/jirbo/adcolony/l:a	Lcom/jirbo/adcolony/l;
    //   47: ldc -73
    //   49: invokevirtual 186	com/jirbo/adcolony/l:b	(Ljava/lang/Object;)Lcom/jirbo/adcolony/l;
    //   52: pop
    //   53: aload_0
    //   54: getfield 52	com/jirbo/adcolony/ADCDownload:c	Ljava/lang/String;
    //   57: ldc -68
    //   59: invokevirtual 194	java/lang/String:startsWith	(Ljava/lang/String;)Z
    //   62: ifeq +1532 -> 1594
    //   65: getstatic 199	android/os/Build$VERSION:SDK_INT	I
    //   68: bipush 10
    //   70: if_icmplt +1524 -> 1594
    //   73: new 169	java/net/URL
    //   76: dup
    //   77: aload_0
    //   78: getfield 52	com/jirbo/adcolony/ADCDownload:c	Ljava/lang/String;
    //   81: invokespecial 170	java/net/URL:<init>	(Ljava/lang/String;)V
    //   84: invokevirtual 174	java/net/URL:openConnection	()Ljava/net/URLConnection;
    //   87: checkcast 201	javax/net/ssl/HttpsURLConnection
    //   90: checkcast 201	javax/net/ssl/HttpsURLConnection
    //   93: astore 8
    //   95: aload_0
    //   96: iconst_1
    //   97: putfield 203	com/jirbo/adcolony/ADCDownload:k	Z
    //   100: aload_0
    //   101: getfield 203	com/jirbo/adcolony/ADCDownload:k	Z
    //   104: ifeq +230 -> 334
    //   107: aload 8
    //   109: ldc -51
    //   111: invokevirtual 208	javax/net/ssl/HttpsURLConnection:setRequestMethod	(Ljava/lang/String;)V
    //   114: aload_0
    //   115: getfield 203	com/jirbo/adcolony/ADCDownload:k	Z
    //   118: ifeq +306 -> 424
    //   121: aload 8
    //   123: iconst_1
    //   124: invokevirtual 212	javax/net/ssl/HttpsURLConnection:setDoOutput	(Z)V
    //   127: aload_0
    //   128: getfield 203	com/jirbo/adcolony/ADCDownload:k	Z
    //   131: ifeq +302 -> 433
    //   134: new 214	java/io/PrintStream
    //   137: dup
    //   138: aload 8
    //   140: invokevirtual 218	javax/net/ssl/HttpsURLConnection:getOutputStream	()Ljava/io/OutputStream;
    //   143: invokespecial 221	java/io/PrintStream:<init>	(Ljava/io/OutputStream;)V
    //   146: astore 9
    //   148: aload 9
    //   150: aload_0
    //   151: getfield 77	com/jirbo/adcolony/ADCDownload:g	Ljava/lang/String;
    //   154: invokevirtual 224	java/io/PrintStream:println	(Ljava/lang/String;)V
    //   157: getstatic 181	com/jirbo/adcolony/l:a	Lcom/jirbo/adcolony/l;
    //   160: ldc -30
    //   162: invokevirtual 229	com/jirbo/adcolony/l:a	(Ljava/lang/String;)Lcom/jirbo/adcolony/l;
    //   165: aload_0
    //   166: getfield 77	com/jirbo/adcolony/ADCDownload:g	Ljava/lang/String;
    //   169: invokevirtual 186	com/jirbo/adcolony/l:b	(Ljava/lang/Object;)Lcom/jirbo/adcolony/l;
    //   172: pop
    //   173: aload_0
    //   174: getfield 203	com/jirbo/adcolony/ADCDownload:k	Z
    //   177: ifeq +273 -> 450
    //   180: aload 8
    //   182: invokevirtual 232	javax/net/ssl/HttpsURLConnection:connect	()V
    //   185: aload_0
    //   186: getfield 203	com/jirbo/adcolony/ADCDownload:k	Z
    //   189: ifeq +14 -> 203
    //   192: aload 8
    //   194: invokevirtual 236	javax/net/ssl/HttpsURLConnection:getResponseCode	()I
    //   197: sipush 200
    //   200: if_icmpeq +21 -> 221
    //   203: aload_0
    //   204: getfield 203	com/jirbo/adcolony/ADCDownload:k	Z
    //   207: ifne +179 -> 386
    //   210: aload 10
    //   212: invokevirtual 237	java/net/HttpURLConnection:getResponseCode	()I
    //   215: sipush 200
    //   218: if_icmpne +168 -> 386
    //   221: aload_0
    //   222: getfield 203	com/jirbo/adcolony/ADCDownload:k	Z
    //   225: ifeq +233 -> 458
    //   228: aload 8
    //   230: invokevirtual 241	javax/net/ssl/HttpsURLConnection:getInputStream	()Ljava/io/InputStream;
    //   233: astore 9
    //   235: new 243	java/lang/StringBuilder
    //   238: dup
    //   239: aload 9
    //   241: invokevirtual 248	java/io/InputStream:available	()I
    //   244: invokespecial 251	java/lang/StringBuilder:<init>	(I)V
    //   247: astore 11
    //   249: aload_0
    //   250: getfield 203	com/jirbo/adcolony/ADCDownload:k	Z
    //   253: ifeq +215 -> 468
    //   256: aload 8
    //   258: invokevirtual 255	javax/net/ssl/HttpsURLConnection:getHeaderFields	()Ljava/util/Map;
    //   261: astore 8
    //   263: aload_0
    //   264: aload 8
    //   266: putfield 257	com/jirbo/adcolony/ADCDownload:m	Ljava/util/Map;
    //   269: sipush 1024
    //   272: newarray <illegal type>
    //   274: astore 8
    //   276: aload 9
    //   278: aload 8
    //   280: iconst_0
    //   281: sipush 1024
    //   284: invokevirtual 261	java/io/InputStream:read	([BII)I
    //   287: istore_1
    //   288: goto +1312 -> 1600
    //   291: iload_2
    //   292: iconst_1
    //   293: iadd
    //   294: istore_2
    //   295: iload_2
    //   296: iload_1
    //   297: if_icmpge +181 -> 478
    //   300: aload 11
    //   302: aload 8
    //   304: iload_2
    //   305: baload
    //   306: i2c
    //   307: invokevirtual 265	java/lang/StringBuilder:append	(C)Ljava/lang/StringBuilder;
    //   310: pop
    //   311: goto -20 -> 291
    //   314: astore 8
    //   316: getstatic 267	com/jirbo/adcolony/l:d	Lcom/jirbo/adcolony/l;
    //   319: ldc 13
    //   321: invokevirtual 186	com/jirbo/adcolony/l:b	(Ljava/lang/Object;)Lcom/jirbo/adcolony/l;
    //   324: pop
    //   325: aload 8
    //   327: invokevirtual 270	java/lang/ArrayIndexOutOfBoundsException:printStackTrace	()V
    //   330: invokestatic 275	com/jirbo/adcolony/AdColony:disable	()V
    //   333: return
    //   334: aload 10
    //   336: ldc -51
    //   338: invokevirtual 276	java/net/HttpURLConnection:setRequestMethod	(Ljava/lang/String;)V
    //   341: goto -227 -> 114
    //   344: astore 8
    //   346: new 243	java/lang/StringBuilder
    //   349: dup
    //   350: invokespecial 277	java/lang/StringBuilder:<init>	()V
    //   353: ldc_w 279
    //   356: invokevirtual 282	java/lang/StringBuilder:append	(Ljava/lang/String;)Ljava/lang/StringBuilder;
    //   359: aload_0
    //   360: getfield 52	com/jirbo/adcolony/ADCDownload:c	Ljava/lang/String;
    //   363: invokevirtual 282	java/lang/StringBuilder:append	(Ljava/lang/String;)Ljava/lang/StringBuilder;
    //   366: ldc_w 284
    //   369: invokevirtual 282	java/lang/StringBuilder:append	(Ljava/lang/String;)Ljava/lang/StringBuilder;
    //   372: aload 8
    //   374: invokevirtual 288	java/io/IOException:toString	()Ljava/lang/String;
    //   377: invokevirtual 282	java/lang/StringBuilder:append	(Ljava/lang/String;)Ljava/lang/StringBuilder;
    //   380: invokevirtual 289	java/lang/StringBuilder:toString	()Ljava/lang/String;
    //   383: invokestatic 291	com/jirbo/adcolony/a:c	(Ljava/lang/String;)V
    //   386: iload 4
    //   388: iconst_3
    //   389: if_icmpne +1144 -> 1533
    //   392: aload_0
    //   393: getfield 52	com/jirbo/adcolony/ADCDownload:c	Ljava/lang/String;
    //   396: ldc_w 293
    //   399: invokevirtual 297	java/lang/String:contains	(Ljava/lang/CharSequence;)Z
    //   402: ifeq +7 -> 409
    //   405: iconst_0
    //   406: putstatic 299	com/jirbo/adcolony/a:p	Z
    //   409: aload_0
    //   410: iconst_0
    //   411: putfield 109	com/jirbo/adcolony/ADCDownload:i	Z
    //   414: aload_0
    //   415: iconst_3
    //   416: putfield 116	com/jirbo/adcolony/ADCDownload:j	I
    //   419: aload_0
    //   420: invokestatic 302	com/jirbo/adcolony/a:a	(Lcom/jirbo/adcolony/j;)V
    //   423: return
    //   424: aload 10
    //   426: iconst_1
    //   427: invokevirtual 303	java/net/HttpURLConnection:setDoOutput	(Z)V
    //   430: goto -303 -> 127
    //   433: new 214	java/io/PrintStream
    //   436: dup
    //   437: aload 10
    //   439: invokevirtual 304	java/net/HttpURLConnection:getOutputStream	()Ljava/io/OutputStream;
    //   442: invokespecial 221	java/io/PrintStream:<init>	(Ljava/io/OutputStream;)V
    //   445: astore 9
    //   447: goto -299 -> 148
    //   450: aload 10
    //   452: invokevirtual 305	java/net/HttpURLConnection:connect	()V
    //   455: goto -270 -> 185
    //   458: aload 10
    //   460: invokevirtual 306	java/net/HttpURLConnection:getInputStream	()Ljava/io/InputStream;
    //   463: astore 9
    //   465: goto -230 -> 235
    //   468: aload 10
    //   470: invokevirtual 307	java/net/HttpURLConnection:getHeaderFields	()Ljava/util/Map;
    //   473: astore 8
    //   475: goto -212 -> 263
    //   478: aload 9
    //   480: aload 8
    //   482: iconst_0
    //   483: sipush 1024
    //   486: invokevirtual 261	java/io/InputStream:read	([BII)I
    //   489: istore_1
    //   490: goto +1110 -> 1600
    //   493: aload 9
    //   495: invokevirtual 310	java/io/InputStream:close	()V
    //   498: aload_0
    //   499: aload 11
    //   501: invokevirtual 289	java/lang/StringBuilder:toString	()Ljava/lang/String;
    //   504: putfield 312	com/jirbo/adcolony/ADCDownload:p	Ljava/lang/String;
    //   507: aload_0
    //   508: aload_0
    //   509: getfield 312	com/jirbo/adcolony/ADCDownload:p	Ljava/lang/String;
    //   512: invokevirtual 315	java/lang/String:length	()I
    //   515: putfield 135	com/jirbo/adcolony/ADCDownload:o	I
    //   518: aload_0
    //   519: getfield 52	com/jirbo/adcolony/ADCDownload:c	Ljava/lang/String;
    //   522: ldc_w 293
    //   525: invokevirtual 297	java/lang/String:contains	(Ljava/lang/CharSequence;)Z
    //   528: ifeq +9 -> 537
    //   531: invokestatic 58	java/lang/System:currentTimeMillis	()J
    //   534: putstatic 318	com/jirbo/adcolony/a:al	J
    //   537: aload_0
    //   538: iconst_1
    //   539: putfield 109	com/jirbo/adcolony/ADCDownload:i	Z
    //   542: aload_0
    //   543: iload 4
    //   545: putfield 116	com/jirbo/adcolony/ADCDownload:j	I
    //   548: aload_0
    //   549: invokestatic 302	com/jirbo/adcolony/a:a	(Lcom/jirbo/adcolony/j;)V
    //   552: return
    //   553: astore 8
    //   555: getstatic 267	com/jirbo/adcolony/l:d	Lcom/jirbo/adcolony/l;
    //   558: new 243	java/lang/StringBuilder
    //   561: dup
    //   562: invokespecial 277	java/lang/StringBuilder:<init>	()V
    //   565: ldc_w 320
    //   568: invokevirtual 282	java/lang/StringBuilder:append	(Ljava/lang/String;)Ljava/lang/StringBuilder;
    //   571: aload 8
    //   573: invokevirtual 321	java/lang/IllegalStateException:toString	()Ljava/lang/String;
    //   576: invokevirtual 282	java/lang/StringBuilder:append	(Ljava/lang/String;)Ljava/lang/StringBuilder;
    //   579: invokevirtual 289	java/lang/StringBuilder:toString	()Ljava/lang/String;
    //   582: invokevirtual 186	com/jirbo/adcolony/l:b	(Ljava/lang/Object;)Lcom/jirbo/adcolony/l;
    //   585: pop
    //   586: aload 8
    //   588: invokevirtual 322	java/lang/IllegalStateException:printStackTrace	()V
    //   591: invokestatic 275	com/jirbo/adcolony/AdColony:disable	()V
    //   594: return
    //   595: astore 8
    //   597: getstatic 267	com/jirbo/adcolony/l:d	Lcom/jirbo/adcolony/l;
    //   600: ldc_w 324
    //   603: invokevirtual 186	com/jirbo/adcolony/l:b	(Ljava/lang/Object;)Lcom/jirbo/adcolony/l;
    //   606: pop
    //   607: invokestatic 275	com/jirbo/adcolony/AdColony:disable	()V
    //   610: return
    //   611: aload 10
    //   613: sipush 30000
    //   616: invokevirtual 327	java/net/HttpURLConnection:setReadTimeout	(I)V
    //   619: aload_0
    //   620: getfield 329	com/jirbo/adcolony/ADCDownload:h	Z
    //   623: ifeq +9 -> 632
    //   626: aload 10
    //   628: iconst_0
    //   629: invokevirtual 332	java/net/HttpURLConnection:setInstanceFollowRedirects	(Z)V
    //   632: aload_0
    //   633: getfield 69	com/jirbo/adcolony/ADCDownload:d	Ljava/io/File;
    //   636: ifnull +355 -> 991
    //   639: aload_0
    //   640: getfield 334	com/jirbo/adcolony/ADCDownload:a	Lcom/jirbo/adcolony/d;
    //   643: ifnull +23 -> 666
    //   646: aload_0
    //   647: getfield 334	com/jirbo/adcolony/ADCDownload:a	Lcom/jirbo/adcolony/d;
    //   650: getfield 337	com/jirbo/adcolony/d:f	Lcom/jirbo/adcolony/ADCStorage;
    //   653: ifnull +13 -> 666
    //   656: aload_0
    //   657: getfield 334	com/jirbo/adcolony/ADCDownload:a	Lcom/jirbo/adcolony/d;
    //   660: getfield 337	com/jirbo/adcolony/d:f	Lcom/jirbo/adcolony/ADCStorage;
    //   663: invokevirtual 341	com/jirbo/adcolony/ADCStorage:b	()V
    //   666: aload_0
    //   667: getfield 69	com/jirbo/adcolony/ADCDownload:d	Ljava/io/File;
    //   670: invokevirtual 344	java/io/File:getAbsolutePath	()Ljava/lang/String;
    //   673: astore 8
    //   675: new 346	java/io/FileOutputStream
    //   678: dup
    //   679: aload 8
    //   681: invokespecial 347	java/io/FileOutputStream:<init>	(Ljava/lang/String;)V
    //   684: astore 9
    //   686: aload 10
    //   688: invokevirtual 306	java/net/HttpURLConnection:getInputStream	()Ljava/io/InputStream;
    //   691: astore 11
    //   693: aload 10
    //   695: invokevirtual 350	java/net/HttpURLConnection:getContentLength	()I
    //   698: istore_2
    //   699: aload_0
    //   700: iconst_0
    //   701: putfield 135	com/jirbo/adcolony/ADCDownload:o	I
    //   704: sipush 1024
    //   707: newarray <illegal type>
    //   709: astore 10
    //   711: aload 11
    //   713: aload 10
    //   715: iconst_0
    //   716: sipush 1024
    //   719: invokevirtual 261	java/io/InputStream:read	([BII)I
    //   722: istore_1
    //   723: aload_0
    //   724: aload_0
    //   725: getfield 72	com/jirbo/adcolony/ADCDownload:e	Ljava/lang/Object;
    //   728: iconst_1
    //   729: invokevirtual 352	com/jirbo/adcolony/ADCDownload:a	(Ljava/lang/Object;Z)V
    //   732: iload_1
    //   733: iconst_m1
    //   734: if_icmpeq +65 -> 799
    //   737: iload_1
    //   738: istore_3
    //   739: iload_2
    //   740: istore 5
    //   742: iload_2
    //   743: ifle +17 -> 760
    //   746: iload_1
    //   747: istore_3
    //   748: iload_1
    //   749: iload_2
    //   750: if_icmple +5 -> 755
    //   753: iload_2
    //   754: istore_3
    //   755: iload_2
    //   756: iload_3
    //   757: isub
    //   758: istore 5
    //   760: aload_0
    //   761: aload_0
    //   762: getfield 135	com/jirbo/adcolony/ADCDownload:o	I
    //   765: iload_3
    //   766: iadd
    //   767: putfield 135	com/jirbo/adcolony/ADCDownload:o	I
    //   770: aload 9
    //   772: aload 10
    //   774: iconst_0
    //   775: iload_3
    //   776: invokevirtual 358	java/io/OutputStream:write	([BII)V
    //   779: aload 11
    //   781: aload 10
    //   783: iconst_0
    //   784: sipush 1024
    //   787: invokevirtual 261	java/io/InputStream:read	([BII)I
    //   790: istore_1
    //   791: iload 5
    //   793: istore_2
    //   794: iload 5
    //   796: ifne -64 -> 732
    //   799: aload_0
    //   800: aload_0
    //   801: getfield 72	com/jirbo/adcolony/ADCDownload:e	Ljava/lang/Object;
    //   804: iconst_0
    //   805: invokevirtual 352	com/jirbo/adcolony/ADCDownload:a	(Ljava/lang/Object;Z)V
    //   808: aload 11
    //   810: invokevirtual 310	java/io/InputStream:close	()V
    //   813: aload 9
    //   815: invokevirtual 361	java/io/OutputStream:flush	()V
    //   818: aload 9
    //   820: invokevirtual 362	java/io/OutputStream:close	()V
    //   823: getstatic 364	com/jirbo/adcolony/l:b	Lcom/jirbo/adcolony/l;
    //   826: ldc_w 366
    //   829: invokevirtual 229	com/jirbo/adcolony/l:a	(Ljava/lang/String;)Lcom/jirbo/adcolony/l;
    //   832: aload_0
    //   833: getfield 52	com/jirbo/adcolony/ADCDownload:c	Ljava/lang/String;
    //   836: invokevirtual 229	com/jirbo/adcolony/l:a	(Ljava/lang/String;)Lcom/jirbo/adcolony/l;
    //   839: ldc_w 368
    //   842: invokevirtual 229	com/jirbo/adcolony/l:a	(Ljava/lang/String;)Lcom/jirbo/adcolony/l;
    //   845: aload 8
    //   847: invokevirtual 186	com/jirbo/adcolony/l:b	(Ljava/lang/Object;)Lcom/jirbo/adcolony/l;
    //   850: pop
    //   851: aload_0
    //   852: iconst_1
    //   853: putfield 109	com/jirbo/adcolony/ADCDownload:i	Z
    //   856: aload_0
    //   857: iload 4
    //   859: putfield 116	com/jirbo/adcolony/ADCDownload:j	I
    //   862: aload_0
    //   863: invokestatic 302	com/jirbo/adcolony/a:a	(Lcom/jirbo/adcolony/j;)V
    //   866: return
    //   867: astore 8
    //   869: getstatic 267	com/jirbo/adcolony/l:d	Lcom/jirbo/adcolony/l;
    //   872: new 243	java/lang/StringBuilder
    //   875: dup
    //   876: invokespecial 277	java/lang/StringBuilder:<init>	()V
    //   879: ldc_w 320
    //   882: invokevirtual 282	java/lang/StringBuilder:append	(Ljava/lang/String;)Ljava/lang/StringBuilder;
    //   885: aload 8
    //   887: invokevirtual 369	java/lang/ArrayIndexOutOfBoundsException:toString	()Ljava/lang/String;
    //   890: invokevirtual 282	java/lang/StringBuilder:append	(Ljava/lang/String;)Ljava/lang/StringBuilder;
    //   893: invokevirtual 289	java/lang/StringBuilder:toString	()Ljava/lang/String;
    //   896: invokevirtual 186	com/jirbo/adcolony/l:b	(Ljava/lang/Object;)Lcom/jirbo/adcolony/l;
    //   899: pop
    //   900: aload 8
    //   902: invokevirtual 270	java/lang/ArrayIndexOutOfBoundsException:printStackTrace	()V
    //   905: invokestatic 275	com/jirbo/adcolony/AdColony:disable	()V
    //   908: return
    //   909: astore 8
    //   911: getstatic 267	com/jirbo/adcolony/l:d	Lcom/jirbo/adcolony/l;
    //   914: new 243	java/lang/StringBuilder
    //   917: dup
    //   918: invokespecial 277	java/lang/StringBuilder:<init>	()V
    //   921: ldc_w 320
    //   924: invokevirtual 282	java/lang/StringBuilder:append	(Ljava/lang/String;)Ljava/lang/StringBuilder;
    //   927: aload 8
    //   929: invokevirtual 321	java/lang/IllegalStateException:toString	()Ljava/lang/String;
    //   932: invokevirtual 282	java/lang/StringBuilder:append	(Ljava/lang/String;)Ljava/lang/StringBuilder;
    //   935: invokevirtual 289	java/lang/StringBuilder:toString	()Ljava/lang/String;
    //   938: invokevirtual 186	com/jirbo/adcolony/l:b	(Ljava/lang/Object;)Lcom/jirbo/adcolony/l;
    //   941: pop
    //   942: aload 8
    //   944: invokevirtual 322	java/lang/IllegalStateException:printStackTrace	()V
    //   947: invokestatic 275	com/jirbo/adcolony/AdColony:disable	()V
    //   950: return
    //   951: astore 8
    //   953: getstatic 267	com/jirbo/adcolony/l:d	Lcom/jirbo/adcolony/l;
    //   956: ldc 13
    //   958: invokevirtual 186	com/jirbo/adcolony/l:b	(Ljava/lang/Object;)Lcom/jirbo/adcolony/l;
    //   961: pop
    //   962: aload 8
    //   964: invokevirtual 270	java/lang/ArrayIndexOutOfBoundsException:printStackTrace	()V
    //   967: invokestatic 275	com/jirbo/adcolony/AdColony:disable	()V
    //   970: return
    //   971: astore 8
    //   973: getstatic 267	com/jirbo/adcolony/l:d	Lcom/jirbo/adcolony/l;
    //   976: ldc 13
    //   978: invokevirtual 186	com/jirbo/adcolony/l:b	(Ljava/lang/Object;)Lcom/jirbo/adcolony/l;
    //   981: pop
    //   982: aload 8
    //   984: invokevirtual 270	java/lang/ArrayIndexOutOfBoundsException:printStackTrace	()V
    //   987: invokestatic 275	com/jirbo/adcolony/AdColony:disable	()V
    //   990: return
    //   991: aload_0
    //   992: getfield 329	com/jirbo/adcolony/ADCDownload:h	Z
    //   995: ifeq +148 -> 1143
    //   998: aload 9
    //   1000: astore 8
    //   1002: aload_0
    //   1003: getfield 52	com/jirbo/adcolony/ADCDownload:c	Ljava/lang/String;
    //   1006: ldc -68
    //   1008: invokevirtual 194	java/lang/String:startsWith	(Ljava/lang/String;)Z
    //   1011: ifeq +42 -> 1053
    //   1014: aload 9
    //   1016: astore 8
    //   1018: getstatic 199	android/os/Build$VERSION:SDK_INT	I
    //   1021: bipush 10
    //   1023: if_icmplt +30 -> 1053
    //   1026: new 169	java/net/URL
    //   1029: dup
    //   1030: aload_0
    //   1031: getfield 52	com/jirbo/adcolony/ADCDownload:c	Ljava/lang/String;
    //   1034: invokespecial 170	java/net/URL:<init>	(Ljava/lang/String;)V
    //   1037: invokevirtual 174	java/net/URL:openConnection	()Ljava/net/URLConnection;
    //   1040: checkcast 201	javax/net/ssl/HttpsURLConnection
    //   1043: checkcast 201	javax/net/ssl/HttpsURLConnection
    //   1046: astore 8
    //   1048: aload_0
    //   1049: iconst_1
    //   1050: putfield 203	com/jirbo/adcolony/ADCDownload:k	Z
    //   1053: aload_0
    //   1054: getfield 203	com/jirbo/adcolony/ADCDownload:k	Z
    //   1057: ifeq +77 -> 1134
    //   1060: aload 8
    //   1062: invokevirtual 236	javax/net/ssl/HttpsURLConnection:getResponseCode	()I
    //   1065: istore_1
    //   1066: iload_1
    //   1067: ifle +76 -> 1143
    //   1070: getstatic 181	com/jirbo/adcolony/l:a	Lcom/jirbo/adcolony/l;
    //   1073: ldc_w 371
    //   1076: invokevirtual 229	com/jirbo/adcolony/l:a	(Ljava/lang/String;)Lcom/jirbo/adcolony/l;
    //   1079: iload_1
    //   1080: invokevirtual 374	com/jirbo/adcolony/l:a	(I)Lcom/jirbo/adcolony/l;
    //   1083: ldc_w 376
    //   1086: invokevirtual 186	com/jirbo/adcolony/l:b	(Ljava/lang/Object;)Lcom/jirbo/adcolony/l;
    //   1089: pop
    //   1090: getstatic 364	com/jirbo/adcolony/l:b	Lcom/jirbo/adcolony/l;
    //   1093: ldc_w 366
    //   1096: invokevirtual 229	com/jirbo/adcolony/l:a	(Ljava/lang/String;)Lcom/jirbo/adcolony/l;
    //   1099: aload_0
    //   1100: getfield 52	com/jirbo/adcolony/ADCDownload:c	Ljava/lang/String;
    //   1103: invokevirtual 186	com/jirbo/adcolony/l:b	(Ljava/lang/Object;)Lcom/jirbo/adcolony/l;
    //   1106: pop
    //   1107: aload_0
    //   1108: ldc 50
    //   1110: putfield 312	com/jirbo/adcolony/ADCDownload:p	Ljava/lang/String;
    //   1113: aload_0
    //   1114: iconst_0
    //   1115: putfield 135	com/jirbo/adcolony/ADCDownload:o	I
    //   1118: aload_0
    //   1119: iconst_1
    //   1120: putfield 109	com/jirbo/adcolony/ADCDownload:i	Z
    //   1123: aload_0
    //   1124: iload 4
    //   1126: putfield 116	com/jirbo/adcolony/ADCDownload:j	I
    //   1129: aload_0
    //   1130: invokestatic 302	com/jirbo/adcolony/a:a	(Lcom/jirbo/adcolony/j;)V
    //   1133: return
    //   1134: aload 10
    //   1136: invokevirtual 237	java/net/HttpURLConnection:getResponseCode	()I
    //   1139: istore_1
    //   1140: goto -74 -> 1066
    //   1143: aload_0
    //   1144: getfield 52	com/jirbo/adcolony/ADCDownload:c	Ljava/lang/String;
    //   1147: ldc -68
    //   1149: invokevirtual 194	java/lang/String:startsWith	(Ljava/lang/String;)Z
    //   1152: ifeq +163 -> 1315
    //   1155: getstatic 199	android/os/Build$VERSION:SDK_INT	I
    //   1158: bipush 10
    //   1160: if_icmplt +155 -> 1315
    //   1163: new 169	java/net/URL
    //   1166: dup
    //   1167: aload_0
    //   1168: getfield 52	com/jirbo/adcolony/ADCDownload:c	Ljava/lang/String;
    //   1171: invokespecial 170	java/net/URL:<init>	(Ljava/lang/String;)V
    //   1174: invokevirtual 174	java/net/URL:openConnection	()Ljava/net/URLConnection;
    //   1177: checkcast 201	javax/net/ssl/HttpsURLConnection
    //   1180: checkcast 201	javax/net/ssl/HttpsURLConnection
    //   1183: astore 8
    //   1185: aload_0
    //   1186: iconst_1
    //   1187: putfield 203	com/jirbo/adcolony/ADCDownload:k	Z
    //   1190: getstatic 181	com/jirbo/adcolony/l:a	Lcom/jirbo/adcolony/l;
    //   1193: ldc_w 378
    //   1196: invokevirtual 186	com/jirbo/adcolony/l:b	(Ljava/lang/Object;)Lcom/jirbo/adcolony/l;
    //   1199: pop
    //   1200: getstatic 181	com/jirbo/adcolony/l:a	Lcom/jirbo/adcolony/l;
    //   1203: ldc_w 380
    //   1206: invokevirtual 186	com/jirbo/adcolony/l:b	(Ljava/lang/Object;)Lcom/jirbo/adcolony/l;
    //   1209: pop
    //   1210: ldc2_w 381
    //   1213: invokestatic 388	java/lang/Thread:sleep	(J)V
    //   1216: getstatic 181	com/jirbo/adcolony/l:a	Lcom/jirbo/adcolony/l;
    //   1219: ldc_w 390
    //   1222: invokevirtual 186	com/jirbo/adcolony/l:b	(Ljava/lang/Object;)Lcom/jirbo/adcolony/l;
    //   1225: pop
    //   1226: aload_0
    //   1227: getfield 203	com/jirbo/adcolony/ADCDownload:k	Z
    //   1230: ifeq +93 -> 1323
    //   1233: aload 8
    //   1235: invokevirtual 241	javax/net/ssl/HttpsURLConnection:getInputStream	()Ljava/io/InputStream;
    //   1238: astore 8
    //   1240: new 243	java/lang/StringBuilder
    //   1243: dup
    //   1244: aload 8
    //   1246: invokevirtual 248	java/io/InputStream:available	()I
    //   1249: invokespecial 251	java/lang/StringBuilder:<init>	(I)V
    //   1252: astore 9
    //   1254: sipush 1024
    //   1257: newarray <illegal type>
    //   1259: astore 10
    //   1261: aload 8
    //   1263: aload 10
    //   1265: iconst_0
    //   1266: sipush 1024
    //   1269: invokevirtual 261	java/io/InputStream:read	([BII)I
    //   1272: istore_1
    //   1273: goto +337 -> 1610
    //   1276: iload_2
    //   1277: iconst_1
    //   1278: iadd
    //   1279: istore_2
    //   1280: iload_2
    //   1281: iload_1
    //   1282: if_icmpge +135 -> 1417
    //   1285: aload 9
    //   1287: aload 10
    //   1289: iload_2
    //   1290: baload
    //   1291: i2c
    //   1292: invokevirtual 265	java/lang/StringBuilder:append	(C)Ljava/lang/StringBuilder;
    //   1295: pop
    //   1296: goto -20 -> 1276
    //   1299: astore 8
    //   1301: getstatic 267	com/jirbo/adcolony/l:d	Lcom/jirbo/adcolony/l;
    //   1304: ldc_w 324
    //   1307: invokevirtual 186	com/jirbo/adcolony/l:b	(Ljava/lang/Object;)Lcom/jirbo/adcolony/l;
    //   1310: pop
    //   1311: invokestatic 275	com/jirbo/adcolony/AdColony:disable	()V
    //   1314: return
    //   1315: aload_0
    //   1316: iconst_0
    //   1317: putfield 203	com/jirbo/adcolony/ADCDownload:k	Z
    //   1320: goto -120 -> 1200
    //   1323: aload 10
    //   1325: invokevirtual 306	java/net/HttpURLConnection:getInputStream	()Ljava/io/InputStream;
    //   1328: astore 8
    //   1330: goto -90 -> 1240
    //   1333: astore 8
    //   1335: getstatic 267	com/jirbo/adcolony/l:d	Lcom/jirbo/adcolony/l;
    //   1338: new 243	java/lang/StringBuilder
    //   1341: dup
    //   1342: invokespecial 277	java/lang/StringBuilder:<init>	()V
    //   1345: ldc_w 320
    //   1348: invokevirtual 282	java/lang/StringBuilder:append	(Ljava/lang/String;)Ljava/lang/StringBuilder;
    //   1351: aload 8
    //   1353: invokevirtual 369	java/lang/ArrayIndexOutOfBoundsException:toString	()Ljava/lang/String;
    //   1356: invokevirtual 282	java/lang/StringBuilder:append	(Ljava/lang/String;)Ljava/lang/StringBuilder;
    //   1359: invokevirtual 289	java/lang/StringBuilder:toString	()Ljava/lang/String;
    //   1362: invokevirtual 186	com/jirbo/adcolony/l:b	(Ljava/lang/Object;)Lcom/jirbo/adcolony/l;
    //   1365: pop
    //   1366: aload 8
    //   1368: invokevirtual 270	java/lang/ArrayIndexOutOfBoundsException:printStackTrace	()V
    //   1371: invokestatic 275	com/jirbo/adcolony/AdColony:disable	()V
    //   1374: return
    //   1375: astore 8
    //   1377: getstatic 267	com/jirbo/adcolony/l:d	Lcom/jirbo/adcolony/l;
    //   1380: new 243	java/lang/StringBuilder
    //   1383: dup
    //   1384: invokespecial 277	java/lang/StringBuilder:<init>	()V
    //   1387: ldc_w 320
    //   1390: invokevirtual 282	java/lang/StringBuilder:append	(Ljava/lang/String;)Ljava/lang/StringBuilder;
    //   1393: aload 8
    //   1395: invokevirtual 321	java/lang/IllegalStateException:toString	()Ljava/lang/String;
    //   1398: invokevirtual 282	java/lang/StringBuilder:append	(Ljava/lang/String;)Ljava/lang/StringBuilder;
    //   1401: invokevirtual 289	java/lang/StringBuilder:toString	()Ljava/lang/String;
    //   1404: invokevirtual 186	com/jirbo/adcolony/l:b	(Ljava/lang/Object;)Lcom/jirbo/adcolony/l;
    //   1407: pop
    //   1408: aload 8
    //   1410: invokevirtual 322	java/lang/IllegalStateException:printStackTrace	()V
    //   1413: invokestatic 275	com/jirbo/adcolony/AdColony:disable	()V
    //   1416: return
    //   1417: aload 8
    //   1419: aload 10
    //   1421: iconst_0
    //   1422: sipush 1024
    //   1425: invokevirtual 261	java/io/InputStream:read	([BII)I
    //   1428: istore_1
    //   1429: goto +181 -> 1610
    //   1432: astore 8
    //   1434: getstatic 267	com/jirbo/adcolony/l:d	Lcom/jirbo/adcolony/l;
    //   1437: ldc 13
    //   1439: invokevirtual 186	com/jirbo/adcolony/l:b	(Ljava/lang/Object;)Lcom/jirbo/adcolony/l;
    //   1442: pop
    //   1443: invokestatic 275	com/jirbo/adcolony/AdColony:disable	()V
    //   1446: aload 8
    //   1448: invokevirtual 322	java/lang/IllegalStateException:printStackTrace	()V
    //   1451: return
    //   1452: astore 8
    //   1454: getstatic 267	com/jirbo/adcolony/l:d	Lcom/jirbo/adcolony/l;
    //   1457: ldc 13
    //   1459: invokevirtual 186	com/jirbo/adcolony/l:b	(Ljava/lang/Object;)Lcom/jirbo/adcolony/l;
    //   1462: pop
    //   1463: aload 8
    //   1465: invokevirtual 270	java/lang/ArrayIndexOutOfBoundsException:printStackTrace	()V
    //   1468: invokestatic 275	com/jirbo/adcolony/AdColony:disable	()V
    //   1471: return
    //   1472: aload 8
    //   1474: invokevirtual 310	java/io/InputStream:close	()V
    //   1477: aload_0
    //   1478: aload 9
    //   1480: invokevirtual 289	java/lang/StringBuilder:toString	()Ljava/lang/String;
    //   1483: putfield 312	com/jirbo/adcolony/ADCDownload:p	Ljava/lang/String;
    //   1486: aload_0
    //   1487: aload_0
    //   1488: getfield 312	com/jirbo/adcolony/ADCDownload:p	Ljava/lang/String;
    //   1491: invokevirtual 315	java/lang/String:length	()I
    //   1494: putfield 135	com/jirbo/adcolony/ADCDownload:o	I
    //   1497: getstatic 364	com/jirbo/adcolony/l:b	Lcom/jirbo/adcolony/l;
    //   1500: ldc_w 366
    //   1503: invokevirtual 229	com/jirbo/adcolony/l:a	(Ljava/lang/String;)Lcom/jirbo/adcolony/l;
    //   1506: aload_0
    //   1507: getfield 52	com/jirbo/adcolony/ADCDownload:c	Ljava/lang/String;
    //   1510: invokevirtual 186	com/jirbo/adcolony/l:b	(Ljava/lang/Object;)Lcom/jirbo/adcolony/l;
    //   1513: pop
    //   1514: goto -663 -> 851
    //   1517: astore 8
    //   1519: getstatic 267	com/jirbo/adcolony/l:d	Lcom/jirbo/adcolony/l;
    //   1522: ldc_w 324
    //   1525: invokevirtual 186	com/jirbo/adcolony/l:b	(Ljava/lang/Object;)Lcom/jirbo/adcolony/l;
    //   1528: pop
    //   1529: invokestatic 275	com/jirbo/adcolony/AdColony:disable	()V
    //   1532: return
    //   1533: iload 4
    //   1535: iconst_1
    //   1536: iadd
    //   1537: bipush 10
    //   1539: imul
    //   1540: sipush 1000
    //   1543: imul
    //   1544: i2l
    //   1545: lstore 6
    //   1547: lload 6
    //   1549: invokestatic 388	java/lang/Thread:sleep	(J)V
    //   1552: getstatic 364	com/jirbo/adcolony/l:b	Lcom/jirbo/adcolony/l;
    //   1555: ldc_w 392
    //   1558: invokevirtual 229	com/jirbo/adcolony/l:a	(Ljava/lang/String;)Lcom/jirbo/adcolony/l;
    //   1561: iload 4
    //   1563: iconst_1
    //   1564: iadd
    //   1565: invokevirtual 374	com/jirbo/adcolony/l:a	(I)Lcom/jirbo/adcolony/l;
    //   1568: ldc_w 394
    //   1571: invokevirtual 186	com/jirbo/adcolony/l:b	(Ljava/lang/Object;)Lcom/jirbo/adcolony/l;
    //   1574: pop
    //   1575: iload 4
    //   1577: iconst_1
    //   1578: iadd
    //   1579: istore 4
    //   1581: goto -1578 -> 3
    //   1584: astore 9
    //   1586: goto -370 -> 1216
    //   1589: astore 8
    //   1591: goto -39 -> 1552
    //   1594: aconst_null
    //   1595: astore 8
    //   1597: goto -1497 -> 100
    //   1600: iload_1
    //   1601: iconst_m1
    //   1602: if_icmpeq -1109 -> 493
    //   1605: iconst_m1
    //   1606: istore_2
    //   1607: goto -1316 -> 291
    //   1610: iload_1
    //   1611: iconst_m1
    //   1612: if_icmpeq -140 -> 1472
    //   1615: iconst_m1
    //   1616: istore_2
    //   1617: goto -341 -> 1276
    // Local variable table:
    //   start	length	slot	name	signature
    //   0	1620	0	this	ADCDownload
    //   287	1326	1	i1	int
    //   291	1326	2	i2	int
    //   738	38	3	i3	int
    //   1	1579	4	i4	int
    //   740	55	5	i5	int
    //   1545	3	6	l1	long
    //   10	293	8	localObject1	Object
    //   314	12	8	localArrayIndexOutOfBoundsException1	ArrayIndexOutOfBoundsException
    //   344	29	8	localIOException	java.io.IOException
    //   473	8	8	localMap	Map
    //   553	34	8	localIllegalStateException1	IllegalStateException
    //   595	1	8	localOutOfMemoryError1	OutOfMemoryError
    //   673	173	8	str	String
    //   867	34	8	localArrayIndexOutOfBoundsException2	ArrayIndexOutOfBoundsException
    //   909	34	8	localIllegalStateException2	IllegalStateException
    //   951	12	8	localArrayIndexOutOfBoundsException3	ArrayIndexOutOfBoundsException
    //   971	12	8	localArrayIndexOutOfBoundsException4	ArrayIndexOutOfBoundsException
    //   1000	262	8	localObject2	Object
    //   1299	1	8	localOutOfMemoryError2	OutOfMemoryError
    //   1328	1	8	localInputStream	java.io.InputStream
    //   1333	34	8	localArrayIndexOutOfBoundsException5	ArrayIndexOutOfBoundsException
    //   1375	43	8	localIllegalStateException3	IllegalStateException
    //   1432	15	8	localIllegalStateException4	IllegalStateException
    //   1452	21	8	localArrayIndexOutOfBoundsException6	ArrayIndexOutOfBoundsException
    //   1517	1	8	localOutOfMemoryError3	OutOfMemoryError
    //   1589	1	8	localInterruptedException	InterruptedException
    //   1595	1	8	localObject3	Object
    //   13	1466	9	localObject4	Object
    //   1584	1	9	localException	Exception
    //   35	1385	10	localObject5	Object
    //   247	562	11	localObject6	Object
    // Exception table:
    //   from	to	target	type
    //   185	203	314	java/lang/ArrayIndexOutOfBoundsException
    //   203	221	314	java/lang/ArrayIndexOutOfBoundsException
    //   221	235	314	java/lang/ArrayIndexOutOfBoundsException
    //   235	263	314	java/lang/ArrayIndexOutOfBoundsException
    //   263	288	314	java/lang/ArrayIndexOutOfBoundsException
    //   300	311	314	java/lang/ArrayIndexOutOfBoundsException
    //   458	465	314	java/lang/ArrayIndexOutOfBoundsException
    //   468	475	314	java/lang/ArrayIndexOutOfBoundsException
    //   478	490	314	java/lang/ArrayIndexOutOfBoundsException
    //   493	498	314	java/lang/ArrayIndexOutOfBoundsException
    //   498	507	314	java/lang/ArrayIndexOutOfBoundsException
    //   507	537	314	java/lang/ArrayIndexOutOfBoundsException
    //   537	552	314	java/lang/ArrayIndexOutOfBoundsException
    //   597	610	314	java/lang/ArrayIndexOutOfBoundsException
    //   15	100	344	java/io/IOException
    //   100	114	344	java/io/IOException
    //   114	127	344	java/io/IOException
    //   127	148	344	java/io/IOException
    //   148	185	344	java/io/IOException
    //   185	203	344	java/io/IOException
    //   203	221	344	java/io/IOException
    //   221	235	344	java/io/IOException
    //   235	263	344	java/io/IOException
    //   263	288	344	java/io/IOException
    //   300	311	344	java/io/IOException
    //   316	333	344	java/io/IOException
    //   334	341	344	java/io/IOException
    //   424	430	344	java/io/IOException
    //   433	447	344	java/io/IOException
    //   450	455	344	java/io/IOException
    //   458	465	344	java/io/IOException
    //   468	475	344	java/io/IOException
    //   478	490	344	java/io/IOException
    //   493	498	344	java/io/IOException
    //   498	507	344	java/io/IOException
    //   507	537	344	java/io/IOException
    //   537	552	344	java/io/IOException
    //   555	594	344	java/io/IOException
    //   597	610	344	java/io/IOException
    //   611	632	344	java/io/IOException
    //   632	666	344	java/io/IOException
    //   666	686	344	java/io/IOException
    //   686	693	344	java/io/IOException
    //   693	711	344	java/io/IOException
    //   711	732	344	java/io/IOException
    //   760	779	344	java/io/IOException
    //   779	791	344	java/io/IOException
    //   799	851	344	java/io/IOException
    //   851	866	344	java/io/IOException
    //   869	908	344	java/io/IOException
    //   911	950	344	java/io/IOException
    //   953	970	344	java/io/IOException
    //   973	990	344	java/io/IOException
    //   991	998	344	java/io/IOException
    //   1002	1014	344	java/io/IOException
    //   1018	1053	344	java/io/IOException
    //   1053	1066	344	java/io/IOException
    //   1070	1133	344	java/io/IOException
    //   1134	1140	344	java/io/IOException
    //   1143	1200	344	java/io/IOException
    //   1200	1210	344	java/io/IOException
    //   1210	1216	344	java/io/IOException
    //   1216	1226	344	java/io/IOException
    //   1226	1240	344	java/io/IOException
    //   1240	1261	344	java/io/IOException
    //   1261	1273	344	java/io/IOException
    //   1285	1296	344	java/io/IOException
    //   1301	1314	344	java/io/IOException
    //   1315	1320	344	java/io/IOException
    //   1323	1330	344	java/io/IOException
    //   1335	1374	344	java/io/IOException
    //   1377	1416	344	java/io/IOException
    //   1417	1429	344	java/io/IOException
    //   1434	1451	344	java/io/IOException
    //   1454	1471	344	java/io/IOException
    //   1472	1477	344	java/io/IOException
    //   1477	1486	344	java/io/IOException
    //   1486	1514	344	java/io/IOException
    //   1519	1532	344	java/io/IOException
    //   185	203	553	java/lang/IllegalStateException
    //   203	221	553	java/lang/IllegalStateException
    //   221	235	553	java/lang/IllegalStateException
    //   235	263	553	java/lang/IllegalStateException
    //   263	288	553	java/lang/IllegalStateException
    //   300	311	553	java/lang/IllegalStateException
    //   458	465	553	java/lang/IllegalStateException
    //   468	475	553	java/lang/IllegalStateException
    //   478	490	553	java/lang/IllegalStateException
    //   493	498	553	java/lang/IllegalStateException
    //   498	507	553	java/lang/IllegalStateException
    //   507	537	553	java/lang/IllegalStateException
    //   537	552	553	java/lang/IllegalStateException
    //   597	610	553	java/lang/IllegalStateException
    //   498	507	595	java/lang/OutOfMemoryError
    //   686	693	867	java/lang/ArrayIndexOutOfBoundsException
    //   686	693	909	java/lang/IllegalStateException
    //   711	732	951	java/lang/ArrayIndexOutOfBoundsException
    //   779	791	971	java/lang/ArrayIndexOutOfBoundsException
    //   1261	1273	1299	java/lang/OutOfMemoryError
    //   1285	1296	1299	java/lang/OutOfMemoryError
    //   1417	1429	1299	java/lang/OutOfMemoryError
    //   1226	1240	1333	java/lang/ArrayIndexOutOfBoundsException
    //   1323	1330	1333	java/lang/ArrayIndexOutOfBoundsException
    //   1226	1240	1375	java/lang/IllegalStateException
    //   1323	1330	1375	java/lang/IllegalStateException
    //   1261	1273	1432	java/lang/IllegalStateException
    //   1285	1296	1432	java/lang/IllegalStateException
    //   1417	1429	1432	java/lang/IllegalStateException
    //   1261	1273	1452	java/lang/ArrayIndexOutOfBoundsException
    //   1285	1296	1452	java/lang/ArrayIndexOutOfBoundsException
    //   1417	1429	1452	java/lang/ArrayIndexOutOfBoundsException
    //   1477	1486	1517	java/lang/OutOfMemoryError
    //   1210	1216	1584	java/lang/Exception
    //   1547	1552	1589	java/lang/InterruptedException
  }
  
  public static abstract interface Listener
  {
    public abstract void on_download_finished(ADCDownload paramADCDownload);
  }
}


/* Location:              /Users/subdiox/Downloads/dex2jar-2.0/net.wargaming.wot.blitz-dex2jar.jar!/com/jirbo/adcolony/ADCDownload.class
 * Java compiler version: 6 (50.0)
 * JD-Core Version:       0.7.1
 */