package com.google.android.gms.maps;

import android.graphics.Bitmap;
import android.location.Location;
import android.os.RemoteException;
import android.view.View;
import com.google.android.gms.common.internal.zzx;
import com.google.android.gms.dynamic.zze;
import com.google.android.gms.maps.internal.IGoogleMapDelegate;
import com.google.android.gms.maps.internal.ILocationSourceDelegate.zza;
import com.google.android.gms.maps.internal.zzb.zza;
import com.google.android.gms.maps.internal.zzd.zza;
import com.google.android.gms.maps.internal.zze.zza;
import com.google.android.gms.maps.internal.zzf.zza;
import com.google.android.gms.maps.internal.zzg.zza;
import com.google.android.gms.maps.internal.zzh;
import com.google.android.gms.maps.internal.zzi.zza;
import com.google.android.gms.maps.internal.zzj.zza;
import com.google.android.gms.maps.internal.zzk.zza;
import com.google.android.gms.maps.internal.zzm.zza;
import com.google.android.gms.maps.internal.zzn.zza;
import com.google.android.gms.maps.internal.zzo.zza;
import com.google.android.gms.maps.internal.zzp.zza;
import com.google.android.gms.maps.internal.zzw.zza;
import com.google.android.gms.maps.model.CameraPosition;
import com.google.android.gms.maps.model.Circle;
import com.google.android.gms.maps.model.CircleOptions;
import com.google.android.gms.maps.model.GroundOverlay;
import com.google.android.gms.maps.model.GroundOverlayOptions;
import com.google.android.gms.maps.model.IndoorBuilding;
import com.google.android.gms.maps.model.LatLng;
import com.google.android.gms.maps.model.Marker;
import com.google.android.gms.maps.model.MarkerOptions;
import com.google.android.gms.maps.model.Polygon;
import com.google.android.gms.maps.model.PolygonOptions;
import com.google.android.gms.maps.model.Polyline;
import com.google.android.gms.maps.model.PolylineOptions;
import com.google.android.gms.maps.model.RuntimeRemoteException;
import com.google.android.gms.maps.model.TileOverlay;
import com.google.android.gms.maps.model.TileOverlayOptions;
import com.google.android.gms.maps.model.internal.zzf;

public final class GoogleMap
{
  public static final int MAP_TYPE_HYBRID = 4;
  public static final int MAP_TYPE_NONE = 0;
  public static final int MAP_TYPE_NORMAL = 1;
  public static final int MAP_TYPE_SATELLITE = 2;
  public static final int MAP_TYPE_TERRAIN = 3;
  private final IGoogleMapDelegate zzaOy;
  private UiSettings zzaOz;
  
  protected GoogleMap(IGoogleMapDelegate paramIGoogleMapDelegate)
  {
    this.zzaOy = ((IGoogleMapDelegate)zzx.zzy(paramIGoogleMapDelegate));
  }
  
  public final Circle addCircle(CircleOptions paramCircleOptions)
  {
    try
    {
      paramCircleOptions = new Circle(this.zzaOy.addCircle(paramCircleOptions));
      return paramCircleOptions;
    }
    catch (RemoteException paramCircleOptions)
    {
      throw new RuntimeRemoteException(paramCircleOptions);
    }
  }
  
  public final GroundOverlay addGroundOverlay(GroundOverlayOptions paramGroundOverlayOptions)
  {
    try
    {
      paramGroundOverlayOptions = this.zzaOy.addGroundOverlay(paramGroundOverlayOptions);
      if (paramGroundOverlayOptions != null)
      {
        paramGroundOverlayOptions = new GroundOverlay(paramGroundOverlayOptions);
        return paramGroundOverlayOptions;
      }
      return null;
    }
    catch (RemoteException paramGroundOverlayOptions)
    {
      throw new RuntimeRemoteException(paramGroundOverlayOptions);
    }
  }
  
  public final Marker addMarker(MarkerOptions paramMarkerOptions)
  {
    try
    {
      paramMarkerOptions = this.zzaOy.addMarker(paramMarkerOptions);
      if (paramMarkerOptions != null)
      {
        paramMarkerOptions = new Marker(paramMarkerOptions);
        return paramMarkerOptions;
      }
      return null;
    }
    catch (RemoteException paramMarkerOptions)
    {
      throw new RuntimeRemoteException(paramMarkerOptions);
    }
  }
  
  public final Polygon addPolygon(PolygonOptions paramPolygonOptions)
  {
    try
    {
      paramPolygonOptions = new Polygon(this.zzaOy.addPolygon(paramPolygonOptions));
      return paramPolygonOptions;
    }
    catch (RemoteException paramPolygonOptions)
    {
      throw new RuntimeRemoteException(paramPolygonOptions);
    }
  }
  
  public final Polyline addPolyline(PolylineOptions paramPolylineOptions)
  {
    try
    {
      paramPolylineOptions = new Polyline(this.zzaOy.addPolyline(paramPolylineOptions));
      return paramPolylineOptions;
    }
    catch (RemoteException paramPolylineOptions)
    {
      throw new RuntimeRemoteException(paramPolylineOptions);
    }
  }
  
  public final TileOverlay addTileOverlay(TileOverlayOptions paramTileOverlayOptions)
  {
    try
    {
      paramTileOverlayOptions = this.zzaOy.addTileOverlay(paramTileOverlayOptions);
      if (paramTileOverlayOptions != null)
      {
        paramTileOverlayOptions = new TileOverlay(paramTileOverlayOptions);
        return paramTileOverlayOptions;
      }
      return null;
    }
    catch (RemoteException paramTileOverlayOptions)
    {
      throw new RuntimeRemoteException(paramTileOverlayOptions);
    }
  }
  
  public final void animateCamera(CameraUpdate paramCameraUpdate)
  {
    try
    {
      this.zzaOy.animateCamera(paramCameraUpdate.zzyS());
      return;
    }
    catch (RemoteException paramCameraUpdate)
    {
      throw new RuntimeRemoteException(paramCameraUpdate);
    }
  }
  
  /* Error */
  public final void animateCamera(CameraUpdate paramCameraUpdate, int paramInt, CancelableCallback paramCancelableCallback)
  {
    // Byte code:
    //   0: aload_0
    //   1: getfield 104	com/google/android/gms/maps/GoogleMap:zzaOy	Lcom/google/android/gms/maps/internal/IGoogleMapDelegate;
    //   4: astore 4
    //   6: aload_1
    //   7: invokevirtual 180	com/google/android/gms/maps/CameraUpdate:zzyS	()Lcom/google/android/gms/dynamic/zzd;
    //   10: astore 5
    //   12: aload_3
    //   13: ifnonnull +17 -> 30
    //   16: aconst_null
    //   17: astore_1
    //   18: aload 4
    //   20: aload 5
    //   22: iload_2
    //   23: aload_1
    //   24: invokeinterface 188 4 0
    //   29: return
    //   30: new 73	com/google/android/gms/maps/GoogleMap$zza
    //   33: dup
    //   34: aload_3
    //   35: invokespecial 191	com/google/android/gms/maps/GoogleMap$zza:<init>	(Lcom/google/android/gms/maps/GoogleMap$CancelableCallback;)V
    //   38: astore_1
    //   39: goto -21 -> 18
    //   42: astore_1
    //   43: new 119	com/google/android/gms/maps/model/RuntimeRemoteException
    //   46: dup
    //   47: aload_1
    //   48: invokespecial 122	com/google/android/gms/maps/model/RuntimeRemoteException:<init>	(Landroid/os/RemoteException;)V
    //   51: athrow
    // Local variable table:
    //   start	length	slot	name	signature
    //   0	52	0	this	GoogleMap
    //   0	52	1	paramCameraUpdate	CameraUpdate
    //   0	52	2	paramInt	int
    //   0	52	3	paramCancelableCallback	CancelableCallback
    //   4	15	4	localIGoogleMapDelegate	IGoogleMapDelegate
    //   10	11	5	localzzd	com.google.android.gms.dynamic.zzd
    // Exception table:
    //   from	to	target	type
    //   0	12	42	android/os/RemoteException
    //   18	29	42	android/os/RemoteException
    //   30	39	42	android/os/RemoteException
  }
  
  /* Error */
  public final void animateCamera(CameraUpdate paramCameraUpdate, CancelableCallback paramCancelableCallback)
  {
    // Byte code:
    //   0: aload_0
    //   1: getfield 104	com/google/android/gms/maps/GoogleMap:zzaOy	Lcom/google/android/gms/maps/internal/IGoogleMapDelegate;
    //   4: astore_3
    //   5: aload_1
    //   6: invokevirtual 180	com/google/android/gms/maps/CameraUpdate:zzyS	()Lcom/google/android/gms/dynamic/zzd;
    //   9: astore 4
    //   11: aload_2
    //   12: ifnonnull +15 -> 27
    //   15: aconst_null
    //   16: astore_1
    //   17: aload_3
    //   18: aload 4
    //   20: aload_1
    //   21: invokeinterface 196 3 0
    //   26: return
    //   27: new 73	com/google/android/gms/maps/GoogleMap$zza
    //   30: dup
    //   31: aload_2
    //   32: invokespecial 191	com/google/android/gms/maps/GoogleMap$zza:<init>	(Lcom/google/android/gms/maps/GoogleMap$CancelableCallback;)V
    //   35: astore_1
    //   36: goto -19 -> 17
    //   39: astore_1
    //   40: new 119	com/google/android/gms/maps/model/RuntimeRemoteException
    //   43: dup
    //   44: aload_1
    //   45: invokespecial 122	com/google/android/gms/maps/model/RuntimeRemoteException:<init>	(Landroid/os/RemoteException;)V
    //   48: athrow
    // Local variable table:
    //   start	length	slot	name	signature
    //   0	49	0	this	GoogleMap
    //   0	49	1	paramCameraUpdate	CameraUpdate
    //   0	49	2	paramCancelableCallback	CancelableCallback
    //   4	14	3	localIGoogleMapDelegate	IGoogleMapDelegate
    //   9	10	4	localzzd	com.google.android.gms.dynamic.zzd
    // Exception table:
    //   from	to	target	type
    //   0	11	39	android/os/RemoteException
    //   17	26	39	android/os/RemoteException
    //   27	36	39	android/os/RemoteException
  }
  
  public final void clear()
  {
    try
    {
      this.zzaOy.clear();
      return;
    }
    catch (RemoteException localRemoteException)
    {
      throw new RuntimeRemoteException(localRemoteException);
    }
  }
  
  public final CameraPosition getCameraPosition()
  {
    try
    {
      CameraPosition localCameraPosition = this.zzaOy.getCameraPosition();
      return localCameraPosition;
    }
    catch (RemoteException localRemoteException)
    {
      throw new RuntimeRemoteException(localRemoteException);
    }
  }
  
  public IndoorBuilding getFocusedBuilding()
  {
    try
    {
      Object localObject = this.zzaOy.getFocusedBuilding();
      if (localObject != null)
      {
        localObject = new IndoorBuilding((com.google.android.gms.maps.model.internal.zzd)localObject);
        return (IndoorBuilding)localObject;
      }
      return null;
    }
    catch (RemoteException localRemoteException)
    {
      throw new RuntimeRemoteException(localRemoteException);
    }
  }
  
  public final int getMapType()
  {
    try
    {
      int i = this.zzaOy.getMapType();
      return i;
    }
    catch (RemoteException localRemoteException)
    {
      throw new RuntimeRemoteException(localRemoteException);
    }
  }
  
  public final float getMaxZoomLevel()
  {
    try
    {
      float f = this.zzaOy.getMaxZoomLevel();
      return f;
    }
    catch (RemoteException localRemoteException)
    {
      throw new RuntimeRemoteException(localRemoteException);
    }
  }
  
  public final float getMinZoomLevel()
  {
    try
    {
      float f = this.zzaOy.getMinZoomLevel();
      return f;
    }
    catch (RemoteException localRemoteException)
    {
      throw new RuntimeRemoteException(localRemoteException);
    }
  }
  
  @Deprecated
  public final Location getMyLocation()
  {
    try
    {
      Location localLocation = this.zzaOy.getMyLocation();
      return localLocation;
    }
    catch (RemoteException localRemoteException)
    {
      throw new RuntimeRemoteException(localRemoteException);
    }
  }
  
  public final Projection getProjection()
  {
    try
    {
      Projection localProjection = new Projection(this.zzaOy.getProjection());
      return localProjection;
    }
    catch (RemoteException localRemoteException)
    {
      throw new RuntimeRemoteException(localRemoteException);
    }
  }
  
  public final UiSettings getUiSettings()
  {
    try
    {
      if (this.zzaOz == null) {
        this.zzaOz = new UiSettings(this.zzaOy.getUiSettings());
      }
      UiSettings localUiSettings = this.zzaOz;
      return localUiSettings;
    }
    catch (RemoteException localRemoteException)
    {
      throw new RuntimeRemoteException(localRemoteException);
    }
  }
  
  public final boolean isBuildingsEnabled()
  {
    try
    {
      boolean bool = this.zzaOy.isBuildingsEnabled();
      return bool;
    }
    catch (RemoteException localRemoteException)
    {
      throw new RuntimeRemoteException(localRemoteException);
    }
  }
  
  public final boolean isIndoorEnabled()
  {
    try
    {
      boolean bool = this.zzaOy.isIndoorEnabled();
      return bool;
    }
    catch (RemoteException localRemoteException)
    {
      throw new RuntimeRemoteException(localRemoteException);
    }
  }
  
  public final boolean isMyLocationEnabled()
  {
    try
    {
      boolean bool = this.zzaOy.isMyLocationEnabled();
      return bool;
    }
    catch (RemoteException localRemoteException)
    {
      throw new RuntimeRemoteException(localRemoteException);
    }
  }
  
  public final boolean isTrafficEnabled()
  {
    try
    {
      boolean bool = this.zzaOy.isTrafficEnabled();
      return bool;
    }
    catch (RemoteException localRemoteException)
    {
      throw new RuntimeRemoteException(localRemoteException);
    }
  }
  
  public final void moveCamera(CameraUpdate paramCameraUpdate)
  {
    try
    {
      this.zzaOy.moveCamera(paramCameraUpdate.zzyS());
      return;
    }
    catch (RemoteException paramCameraUpdate)
    {
      throw new RuntimeRemoteException(paramCameraUpdate);
    }
  }
  
  public final void setBuildingsEnabled(boolean paramBoolean)
  {
    try
    {
      this.zzaOy.setBuildingsEnabled(paramBoolean);
      return;
    }
    catch (RemoteException localRemoteException)
    {
      throw new RuntimeRemoteException(localRemoteException);
    }
  }
  
  public final void setContentDescription(String paramString)
  {
    try
    {
      this.zzaOy.setContentDescription(paramString);
      return;
    }
    catch (RemoteException paramString)
    {
      throw new RuntimeRemoteException(paramString);
    }
  }
  
  public final boolean setIndoorEnabled(boolean paramBoolean)
  {
    try
    {
      paramBoolean = this.zzaOy.setIndoorEnabled(paramBoolean);
      return paramBoolean;
    }
    catch (RemoteException localRemoteException)
    {
      throw new RuntimeRemoteException(localRemoteException);
    }
  }
  
  public final void setInfoWindowAdapter(final InfoWindowAdapter paramInfoWindowAdapter)
  {
    if (paramInfoWindowAdapter == null) {}
    try
    {
      this.zzaOy.setInfoWindowAdapter(null);
      return;
    }
    catch (RemoteException paramInfoWindowAdapter)
    {
      throw new RuntimeRemoteException(paramInfoWindowAdapter);
    }
    this.zzaOy.setInfoWindowAdapter(new zzd.zza()
    {
      public com.google.android.gms.dynamic.zzd zzf(zzf paramAnonymouszzf)
      {
        return zze.zzB(paramInfoWindowAdapter.getInfoWindow(new Marker(paramAnonymouszzf)));
      }
      
      public com.google.android.gms.dynamic.zzd zzg(zzf paramAnonymouszzf)
      {
        return zze.zzB(paramInfoWindowAdapter.getInfoContents(new Marker(paramAnonymouszzf)));
      }
    });
  }
  
  public final void setLocationSource(final LocationSource paramLocationSource)
  {
    if (paramLocationSource == null) {}
    try
    {
      this.zzaOy.setLocationSource(null);
      return;
    }
    catch (RemoteException paramLocationSource)
    {
      throw new RuntimeRemoteException(paramLocationSource);
    }
    this.zzaOy.setLocationSource(new ILocationSourceDelegate.zza()
    {
      public void activate(final zzh paramAnonymouszzh)
      {
        paramLocationSource.activate(new LocationSource.OnLocationChangedListener()
        {
          public void onLocationChanged(Location paramAnonymous2Location)
          {
            try
            {
              paramAnonymouszzh.zzd(paramAnonymous2Location);
              return;
            }
            catch (RemoteException paramAnonymous2Location)
            {
              throw new RuntimeRemoteException(paramAnonymous2Location);
            }
          }
        });
      }
      
      public void deactivate()
      {
        paramLocationSource.deactivate();
      }
    });
  }
  
  public final void setMapType(int paramInt)
  {
    try
    {
      this.zzaOy.setMapType(paramInt);
      return;
    }
    catch (RemoteException localRemoteException)
    {
      throw new RuntimeRemoteException(localRemoteException);
    }
  }
  
  public final void setMyLocationEnabled(boolean paramBoolean)
  {
    try
    {
      this.zzaOy.setMyLocationEnabled(paramBoolean);
      return;
    }
    catch (RemoteException localRemoteException)
    {
      throw new RuntimeRemoteException(localRemoteException);
    }
  }
  
  public final void setOnCameraChangeListener(final OnCameraChangeListener paramOnCameraChangeListener)
  {
    if (paramOnCameraChangeListener == null) {}
    try
    {
      this.zzaOy.setOnCameraChangeListener(null);
      return;
    }
    catch (RemoteException paramOnCameraChangeListener)
    {
      throw new RuntimeRemoteException(paramOnCameraChangeListener);
    }
    this.zzaOy.setOnCameraChangeListener(new zze.zza()
    {
      public void onCameraChange(CameraPosition paramAnonymousCameraPosition)
      {
        paramOnCameraChangeListener.onCameraChange(paramAnonymousCameraPosition);
      }
    });
  }
  
  public final void setOnIndoorStateChangeListener(final OnIndoorStateChangeListener paramOnIndoorStateChangeListener)
  {
    if (paramOnIndoorStateChangeListener == null) {}
    try
    {
      this.zzaOy.setOnIndoorStateChangeListener(null);
      return;
    }
    catch (RemoteException paramOnIndoorStateChangeListener)
    {
      throw new RuntimeRemoteException(paramOnIndoorStateChangeListener);
    }
    this.zzaOy.setOnIndoorStateChangeListener(new zzf.zza()
    {
      public void onIndoorBuildingFocused()
      {
        paramOnIndoorStateChangeListener.onIndoorBuildingFocused();
      }
      
      public void zza(com.google.android.gms.maps.model.internal.zzd paramAnonymouszzd)
      {
        paramOnIndoorStateChangeListener.onIndoorLevelActivated(new IndoorBuilding(paramAnonymouszzd));
      }
    });
  }
  
  public final void setOnInfoWindowClickListener(final OnInfoWindowClickListener paramOnInfoWindowClickListener)
  {
    if (paramOnInfoWindowClickListener == null) {}
    try
    {
      this.zzaOy.setOnInfoWindowClickListener(null);
      return;
    }
    catch (RemoteException paramOnInfoWindowClickListener)
    {
      throw new RuntimeRemoteException(paramOnInfoWindowClickListener);
    }
    this.zzaOy.setOnInfoWindowClickListener(new zzg.zza()
    {
      public void zze(zzf paramAnonymouszzf)
      {
        paramOnInfoWindowClickListener.onInfoWindowClick(new Marker(paramAnonymouszzf));
      }
    });
  }
  
  public final void setOnMapClickListener(final OnMapClickListener paramOnMapClickListener)
  {
    if (paramOnMapClickListener == null) {}
    try
    {
      this.zzaOy.setOnMapClickListener(null);
      return;
    }
    catch (RemoteException paramOnMapClickListener)
    {
      throw new RuntimeRemoteException(paramOnMapClickListener);
    }
    this.zzaOy.setOnMapClickListener(new zzi.zza()
    {
      public void onMapClick(LatLng paramAnonymousLatLng)
      {
        paramOnMapClickListener.onMapClick(paramAnonymousLatLng);
      }
    });
  }
  
  public void setOnMapLoadedCallback(final OnMapLoadedCallback paramOnMapLoadedCallback)
  {
    if (paramOnMapLoadedCallback == null) {}
    try
    {
      this.zzaOy.setOnMapLoadedCallback(null);
      return;
    }
    catch (RemoteException paramOnMapLoadedCallback)
    {
      throw new RuntimeRemoteException(paramOnMapLoadedCallback);
    }
    this.zzaOy.setOnMapLoadedCallback(new zzj.zza()
    {
      public void onMapLoaded()
        throws RemoteException
      {
        paramOnMapLoadedCallback.onMapLoaded();
      }
    });
  }
  
  public final void setOnMapLongClickListener(final OnMapLongClickListener paramOnMapLongClickListener)
  {
    if (paramOnMapLongClickListener == null) {}
    try
    {
      this.zzaOy.setOnMapLongClickListener(null);
      return;
    }
    catch (RemoteException paramOnMapLongClickListener)
    {
      throw new RuntimeRemoteException(paramOnMapLongClickListener);
    }
    this.zzaOy.setOnMapLongClickListener(new zzk.zza()
    {
      public void onMapLongClick(LatLng paramAnonymousLatLng)
      {
        paramOnMapLongClickListener.onMapLongClick(paramAnonymousLatLng);
      }
    });
  }
  
  public final void setOnMarkerClickListener(final OnMarkerClickListener paramOnMarkerClickListener)
  {
    if (paramOnMarkerClickListener == null) {}
    try
    {
      this.zzaOy.setOnMarkerClickListener(null);
      return;
    }
    catch (RemoteException paramOnMarkerClickListener)
    {
      throw new RuntimeRemoteException(paramOnMarkerClickListener);
    }
    this.zzaOy.setOnMarkerClickListener(new zzm.zza()
    {
      public boolean zza(zzf paramAnonymouszzf)
      {
        return paramOnMarkerClickListener.onMarkerClick(new Marker(paramAnonymouszzf));
      }
    });
  }
  
  public final void setOnMarkerDragListener(final OnMarkerDragListener paramOnMarkerDragListener)
  {
    if (paramOnMarkerDragListener == null) {}
    try
    {
      this.zzaOy.setOnMarkerDragListener(null);
      return;
    }
    catch (RemoteException paramOnMarkerDragListener)
    {
      throw new RuntimeRemoteException(paramOnMarkerDragListener);
    }
    this.zzaOy.setOnMarkerDragListener(new zzn.zza()
    {
      public void zzb(zzf paramAnonymouszzf)
      {
        paramOnMarkerDragListener.onMarkerDragStart(new Marker(paramAnonymouszzf));
      }
      
      public void zzc(zzf paramAnonymouszzf)
      {
        paramOnMarkerDragListener.onMarkerDragEnd(new Marker(paramAnonymouszzf));
      }
      
      public void zzd(zzf paramAnonymouszzf)
      {
        paramOnMarkerDragListener.onMarkerDrag(new Marker(paramAnonymouszzf));
      }
    });
  }
  
  public final void setOnMyLocationButtonClickListener(final OnMyLocationButtonClickListener paramOnMyLocationButtonClickListener)
  {
    if (paramOnMyLocationButtonClickListener == null) {}
    try
    {
      this.zzaOy.setOnMyLocationButtonClickListener(null);
      return;
    }
    catch (RemoteException paramOnMyLocationButtonClickListener)
    {
      throw new RuntimeRemoteException(paramOnMyLocationButtonClickListener);
    }
    this.zzaOy.setOnMyLocationButtonClickListener(new zzo.zza()
    {
      public boolean onMyLocationButtonClick()
        throws RemoteException
      {
        return paramOnMyLocationButtonClickListener.onMyLocationButtonClick();
      }
    });
  }
  
  @Deprecated
  public final void setOnMyLocationChangeListener(final OnMyLocationChangeListener paramOnMyLocationChangeListener)
  {
    if (paramOnMyLocationChangeListener == null) {}
    try
    {
      this.zzaOy.setOnMyLocationChangeListener(null);
      return;
    }
    catch (RemoteException paramOnMyLocationChangeListener)
    {
      throw new RuntimeRemoteException(paramOnMyLocationChangeListener);
    }
    this.zzaOy.setOnMyLocationChangeListener(new zzp.zza()
    {
      public void zzq(com.google.android.gms.dynamic.zzd paramAnonymouszzd)
      {
        paramOnMyLocationChangeListener.onMyLocationChange((Location)zze.zzp(paramAnonymouszzd));
      }
    });
  }
  
  public final void setPadding(int paramInt1, int paramInt2, int paramInt3, int paramInt4)
  {
    try
    {
      this.zzaOy.setPadding(paramInt1, paramInt2, paramInt3, paramInt4);
      return;
    }
    catch (RemoteException localRemoteException)
    {
      throw new RuntimeRemoteException(localRemoteException);
    }
  }
  
  public final void setTrafficEnabled(boolean paramBoolean)
  {
    try
    {
      this.zzaOy.setTrafficEnabled(paramBoolean);
      return;
    }
    catch (RemoteException localRemoteException)
    {
      throw new RuntimeRemoteException(localRemoteException);
    }
  }
  
  public final void snapshot(SnapshotReadyCallback paramSnapshotReadyCallback)
  {
    snapshot(paramSnapshotReadyCallback, null);
  }
  
  public final void snapshot(final SnapshotReadyCallback paramSnapshotReadyCallback, Bitmap paramBitmap)
  {
    if (paramBitmap != null) {}
    for (paramBitmap = zze.zzB(paramBitmap);; paramBitmap = null)
    {
      paramBitmap = (zze)paramBitmap;
      try
      {
        this.zzaOy.snapshot(new zzw.zza()
        {
          public void onSnapshotReady(Bitmap paramAnonymousBitmap)
            throws RemoteException
          {
            paramSnapshotReadyCallback.onSnapshotReady(paramAnonymousBitmap);
          }
          
          public void zzr(com.google.android.gms.dynamic.zzd paramAnonymouszzd)
            throws RemoteException
          {
            paramSnapshotReadyCallback.onSnapshotReady((Bitmap)zze.zzp(paramAnonymouszzd));
          }
        }, paramBitmap);
        return;
      }
      catch (RemoteException paramSnapshotReadyCallback)
      {
        throw new RuntimeRemoteException(paramSnapshotReadyCallback);
      }
    }
  }
  
  public final void stopAnimation()
  {
    try
    {
      this.zzaOy.stopAnimation();
      return;
    }
    catch (RemoteException localRemoteException)
    {
      throw new RuntimeRemoteException(localRemoteException);
    }
  }
  
  IGoogleMapDelegate zzyU()
  {
    return this.zzaOy;
  }
  
  public static abstract interface CancelableCallback
  {
    public abstract void onCancel();
    
    public abstract void onFinish();
  }
  
  public static abstract interface InfoWindowAdapter
  {
    public abstract View getInfoContents(Marker paramMarker);
    
    public abstract View getInfoWindow(Marker paramMarker);
  }
  
  public static abstract interface OnCameraChangeListener
  {
    public abstract void onCameraChange(CameraPosition paramCameraPosition);
  }
  
  public static abstract interface OnIndoorStateChangeListener
  {
    public abstract void onIndoorBuildingFocused();
    
    public abstract void onIndoorLevelActivated(IndoorBuilding paramIndoorBuilding);
  }
  
  public static abstract interface OnInfoWindowClickListener
  {
    public abstract void onInfoWindowClick(Marker paramMarker);
  }
  
  public static abstract interface OnMapClickListener
  {
    public abstract void onMapClick(LatLng paramLatLng);
  }
  
  public static abstract interface OnMapLoadedCallback
  {
    public abstract void onMapLoaded();
  }
  
  public static abstract interface OnMapLongClickListener
  {
    public abstract void onMapLongClick(LatLng paramLatLng);
  }
  
  public static abstract interface OnMarkerClickListener
  {
    public abstract boolean onMarkerClick(Marker paramMarker);
  }
  
  public static abstract interface OnMarkerDragListener
  {
    public abstract void onMarkerDrag(Marker paramMarker);
    
    public abstract void onMarkerDragEnd(Marker paramMarker);
    
    public abstract void onMarkerDragStart(Marker paramMarker);
  }
  
  public static abstract interface OnMyLocationButtonClickListener
  {
    public abstract boolean onMyLocationButtonClick();
  }
  
  @Deprecated
  public static abstract interface OnMyLocationChangeListener
  {
    public abstract void onMyLocationChange(Location paramLocation);
  }
  
  public static abstract interface SnapshotReadyCallback
  {
    public abstract void onSnapshotReady(Bitmap paramBitmap);
  }
  
  private static final class zza
    extends zzb.zza
  {
    private final GoogleMap.CancelableCallback zzaOQ;
    
    zza(GoogleMap.CancelableCallback paramCancelableCallback)
    {
      this.zzaOQ = paramCancelableCallback;
    }
    
    public void onCancel()
    {
      this.zzaOQ.onCancel();
    }
    
    public void onFinish()
    {
      this.zzaOQ.onFinish();
    }
  }
}


/* Location:              /Users/subdiox/Downloads/dex2jar-2.0/net.wargaming.wot.blitz-dex2jar.jar!/com/google/android/gms/maps/GoogleMap.class
 * Java compiler version: 6 (50.0)
 * JD-Core Version:       0.7.1
 */